[{"contact":{"phone":"555-555-5555","fullName":"Homer Simpson","id":"1","email":"homer.simpson@gmail.com"}},{"contact":{"phone":"444-555-5445","fullName":"Marge Simpson","id":"2","email":"marge.simpson@gmail.com"}},{"contact":{"phone":"777-555-5225","fullName":"Bart Simpson","id":"3","email":"lisa.simpson@gmail.com"}},{"contact":{"phone":"333-555-1223","fullName":"Maggie O'Simpson","id":"4","email":"maggie.simpson@gmail.com"}},{"contact":{"phone":"414-685-8135","fullName":"Carl Carlson","id":"1AD5A30B-BBFF-9609-063FC798612EC96C","email":"carl@springfieldpower.com"}}]